memshell/__init__.py
memshell/main.py
memshell-0.5.4.dist-info/METADATA
memshell-0.5.4.dist-info/WHEEL
memshell-0.5.4.dist-info/RECORD
