Metadata-Version: 2.4
Name: memshell
Version: 0.5.4
Summary: Interactive shell object that remembers previous commands, path and env variables
Author-email: Anthony Post <post.anthony@icloud.com>
License: MIT
Requires-Python: >=3.8
